datamarkin/__init__.py
datamarkin/core.py
datamarkin-0.1.0.dist-info/LICENSE
datamarkin-0.1.0.dist-info/METADATA
datamarkin-0.1.0.dist-info/WHEEL
datamarkin-0.1.0.dist-info/top_level.txt
datamarkin-0.1.0.dist-info/RECORD
