Metadata-Version: 2.1
Name: datamarkin
Version: 0.1.0
Summary: Reusable computer vision tools
Home-page: https://github.com/datamarkin/visionflow
Author: Datamarkin
Author-email: support@datamarkin.com
License: MIT License
Classifier: Development Status :: 1 - Planning
Classifier: Intended Audience :: Science/Research
Classifier: License :: OSI Approved :: MIT License
Classifier: Operating System :: OS Independent
Classifier: Programming Language :: Python :: 3
Requires-Python: >=3
License-File: LICENSE
